<?xml version="1.1" encoding="UTF-8"?>

<!--
 * See the NOTICE file distributed with this work for additional
 * information regarding copyright ownership.
 *
 * This is free software; you can redistribute it and/or modify it
 * under the terms of the GNU Lesser General Public License as
 * published by the Free Software Foundation; either version 2.1 of
 * the License, or (at your option) any later version.
 *
 * This software is distributed in the hope that it will be useful,
 * but WITHOUT ANY WARRANTY; without even the implied warranty of
 * MERCHANTABILITY or FITNESS FOR A PARTICULAR PURPOSE. See the GNU
 * Lesser General Public License for more details.
 *
 * You should have received a copy of the GNU Lesser General Public
 * License along with this software; if not, write to the Free
 * Software Foundation, Inc., 51 Franklin St, Fifth Floor, Boston, MA
 * 02110-1301 USA, or see the FSF site: http://www.fsf.org.
-->

<xwikidoc version="1.4" reference="Analytics.Code.Macros.MostViewedPages" locale="">
  <web>Analytics.Code.Macros</web>
  <name>MostViewedPages</name>
  <language/>
  <defaultLanguage/>
  <translation>0</translation>
  <creator>xwiki:XWiki.Admin</creator>
  <parent>Analytics.Code.Macros.WebHome</parent>
  <author>xwiki:XWiki.Admin</author>
  <contentAuthor>xwiki:XWiki.Admin</contentAuthor>
  <version>1.1</version>
  <title>MostViewedPages</title>
  <comment/>
  <minorEdit>false</minorEdit>
  <syntaxId>xwiki/2.1</syntaxId>
  <hidden>true</hidden>
  <content>{{mostViewedPages}}</content>
  <object>
    <name>Analytics.Code.Macros.MostViewedPages</name>
    <number>0</number>
    <className>XWiki.JavaScriptExtension</className>
    <guid>5b6bb6f7-68aa-437e-9c20-a36dcb3ea9de</guid>
    <class>
      <name>XWiki.JavaScriptExtension</name>
      <customClass/>
      <customMapping/>
      <defaultViewSheet/>
      <defaultEditSheet/>
      <defaultWeb/>
      <nameField/>
      <validationScript/>
      <cache>
        <cache>0</cache>
        <defaultValue>long</defaultValue>
        <disabled>0</disabled>
        <displayType>select</displayType>
        <freeText>forbidden</freeText>
        <largeStorage>0</largeStorage>
        <multiSelect>0</multiSelect>
        <name>cache</name>
        <number>5</number>
        <prettyName>Caching policy</prettyName>
        <relationalStorage>0</relationalStorage>
        <separator> </separator>
        <separators>|, </separators>
        <size>1</size>
        <unmodifiable>0</unmodifiable>
        <values>long|short|default|forbid</values>
        <classType>com.xpn.xwiki.objects.classes.StaticListClass</classType>
      </cache>
      <code>
        <contenttype>PureText</contenttype>
        <disabled>0</disabled>
        <editor>PureText</editor>
        <name>code</name>
        <number>2</number>
        <prettyName>Code</prettyName>
        <rows>20</rows>
        <size>50</size>
        <unmodifiable>0</unmodifiable>
        <classType>com.xpn.xwiki.objects.classes.TextAreaClass</classType>
      </code>
      <name>
        <disabled>0</disabled>
        <name>name</name>
        <number>1</number>
        <prettyName>Name</prettyName>
        <size>30</size>
        <unmodifiable>0</unmodifiable>
        <classType>com.xpn.xwiki.objects.classes.StringClass</classType>
      </name>
      <parse>
        <disabled>0</disabled>
        <displayFormType>select</displayFormType>
        <displayType>yesno</displayType>
        <name>parse</name>
        <number>4</number>
        <prettyName>Parse content</prettyName>
        <unmodifiable>0</unmodifiable>
        <classType>com.xpn.xwiki.objects.classes.BooleanClass</classType>
      </parse>
      <use>
        <cache>0</cache>
        <disabled>0</disabled>
        <displayType>select</displayType>
        <freeText>forbidden</freeText>
        <largeStorage>0</largeStorage>
        <multiSelect>0</multiSelect>
        <name>use</name>
        <number>3</number>
        <prettyName>Use this extension</prettyName>
        <relationalStorage>0</relationalStorage>
        <separator> </separator>
        <separators>|, </separators>
        <size>1</size>
        <unmodifiable>0</unmodifiable>
        <values>currentPage|onDemand|always</values>
        <classType>com.xpn.xwiki.objects.classes.StaticListClass</classType>
      </use>
    </class>
    <property>
      <cache>long</cache>
    </property>
    <property>
      <code>define('mostViewedPagesTranslation', {
  prefix: 'analytics.mostViewedPages.header.',
  keys: [
    'year',
    'title',
    'visits',
    'hits',
    'timeSpent',
    'entryNbVisits',
    'entryNbActions',
    'bounceRate',
    'exitRate'
  ]
});


require(['jquery', 'xwiki-l10n!mostViewedPagesTranslation'], function ($, l10n) {


  function constructUrl(element) {
    const paramString = $.param({
      module: 'API',
      method: 'Actions.getPageTitles',
      idSite: element.dataset.idSite,
      period: element.dataset.period,
      date: element.dataset.date,
      format: 'json',
      filter_sort_column: 'nb_hits',
      filter_sort_order: 'desc',
      token_auth: element.dataset.authToken
    });
    return element.dataset.ipMatomo + 'index.php?' + paramString;
  };


  function createHeader(headersTranslations) {
    let headerRow = document.createElement('tr');
    headersTranslations.forEach(header =&gt; {
      let headerCell = document.createElement('th');
      headerCell.classList.add('xwiki-mostviewedpages-header');
      headerCell.textContent = l10n[header];
      headerRow.appendChild(headerCell);
    });
return headerRow;
    };
function createHeader(headersTranslations) {
  console.log(l10n);
  let headerRow = $('&lt;tr class="table"&gt;&lt;/tr&gt;');
  headersTranslations.forEach(header =&gt; {
    let headerCell = $(`&lt;th class='xwiki-mostviewedpages-header'&gt;${l10n[header]}&lt;/th&gt;`);
    headerRow.append(headerCell);
  });
  return headerRow[0];
};


function createRowFromData(headers, dataItem, index) {
  let row = $('&lt;tr&gt;');
  headers.forEach(header =&gt; {
    let cell = $(`&lt;td class='xwiki-mostviewedpages-cell'&gt; ${dataItem[header] !== undefined ? dataItem[header] : ""}&lt;/td&gt;`);
    row.append(cell);
  });
  return row[0]; // returns the first (and only) element, which is the raw DOM node
};


function handleArrayData(fragment, headers, data) {
  data.forEach((item, index) =&gt; {
    let row = createRowFromData(headers, item, index);
    fragment.appendChild(row);
  });
};


function handleJsonData(fragment, headers, data) {
  for (let year in data) {
    data[year].forEach((item, index) =&gt; {
      // Add 'year' to each item. At some point, we might want to unify the data from different years. For the time being, I don't know how Matomo handles data from multiple years.
      item.year = year;
      let row = createRowFromData(headers, item, index);
      fragment.appendChild(row);
    });
  }
};


function createTable(container) {
  let table = document.createElement('table');
  let thead = document.createElement('thead');
  let tbody = document.createElement('tbody');
  let fragment = document.createDocumentFragment();

  table.classList.add('table');
  table.classList.add('table-hover');
  table.classList.add('table-striped');

  let url = constructUrl(container);
  $.getJSON(url)
    .done(function (data) {
      let headers = Array.isArray(data)
        ? ['title', 'visits', 'hits', 'timeSpent', 'entryNbVisits', 'entryNbActions', 'bounceRate', 'exitRate']
        : ['year', 'title', 'visits', 'hits', 'timeSpent', 'entryNbVisits', 'entryNbActions', 'bounceRate', 'exitRate'];
      let jsonKeys = Array.isArray(data)
        ? ['label', 'nb_visits', 'nb_hits', 'sum_time_spent', 'entry_nb_visits', 'entry_nb_actions', 'bounce_rate', 'exit_rate']
        : ['year', 'label', 'nb_visits', 'nb_hits', 'sum_time_spent', 'entry_nb_visits', 'entry_nb_actions', 'bounce_rate', 'exit_rate'];
      thead.appendChild(createHeader(headers));
      if (Array.isArray(data)) {
        handleArrayData(fragment, jsonKeys, data);
      } else {
        handleJsonData(fragment, jsonKeys, data);
      }
      tbody.appendChild(fragment);
      table.appendChild(thead);
      table.appendChild(tbody);
      container.appendChild(table);
    })
    .fail(function (jqxhr, textStatus, error) {
      let err = textStatus + ", " + error;
      console.log("Request Failed: " + err);
      new XWiki.widgets.Notification(l10n.get('error', error), 'error');
    });
};


$(function () {
  let containers = document.querySelectorAll('.mostViewedPages');
  containers.forEach((container, index) =&gt; {
    createTable(container);
  });
});
});
</code>
    </property>
    <property>
      <name/>
    </property>
    <property>
      <parse/>
    </property>
    <property>
      <use>onDemand</use>
    </property>
  </object>
  <object>
    <name>Analytics.Code.Macros.MostViewedPages</name>
    <number>0</number>
    <className>XWiki.StyleSheetExtension</className>
    <guid>d76078ba-f6aa-498b-9d7b-5b221b9c3e30</guid>
    <class>
      <name>XWiki.StyleSheetExtension</name>
      <customClass/>
      <customMapping/>
      <defaultViewSheet/>
      <defaultEditSheet/>
      <defaultWeb/>
      <nameField/>
      <validationScript/>
      <cache>
        <cache>0</cache>
        <defaultValue>long</defaultValue>
        <disabled>0</disabled>
        <displayType>select</displayType>
        <freeText>forbidden</freeText>
        <largeStorage>0</largeStorage>
        <multiSelect>0</multiSelect>
        <name>cache</name>
        <number>5</number>
        <prettyName>Caching policy</prettyName>
        <relationalStorage>0</relationalStorage>
        <separator> </separator>
        <separators>|, </separators>
        <size>1</size>
        <unmodifiable>0</unmodifiable>
        <values>long|short|default|forbid</values>
        <classType>com.xpn.xwiki.objects.classes.StaticListClass</classType>
      </cache>
      <code>
        <contenttype>PureText</contenttype>
        <disabled>0</disabled>
        <editor>PureText</editor>
        <name>code</name>
        <number>2</number>
        <prettyName>Code</prettyName>
        <rows>20</rows>
        <size>50</size>
        <unmodifiable>0</unmodifiable>
        <classType>com.xpn.xwiki.objects.classes.TextAreaClass</classType>
      </code>
      <contentType>
        <cache>0</cache>
        <disabled>0</disabled>
        <displayType>select</displayType>
        <freeText>forbidden</freeText>
        <largeStorage>0</largeStorage>
        <multiSelect>0</multiSelect>
        <name>contentType</name>
        <number>6</number>
        <prettyName>Content Type</prettyName>
        <relationalStorage>0</relationalStorage>
        <separator> </separator>
        <separators>|, </separators>
        <size>1</size>
        <unmodifiable>0</unmodifiable>
        <values>CSS|LESS</values>
        <classType>com.xpn.xwiki.objects.classes.StaticListClass</classType>
      </contentType>
      <name>
        <disabled>0</disabled>
        <name>name</name>
        <number>1</number>
        <prettyName>Name</prettyName>
        <size>30</size>
        <unmodifiable>0</unmodifiable>
        <classType>com.xpn.xwiki.objects.classes.StringClass</classType>
      </name>
      <parse>
        <disabled>0</disabled>
        <displayFormType>select</displayFormType>
        <displayType>yesno</displayType>
        <name>parse</name>
        <number>4</number>
        <prettyName>Parse content</prettyName>
        <unmodifiable>0</unmodifiable>
        <classType>com.xpn.xwiki.objects.classes.BooleanClass</classType>
      </parse>
      <use>
        <cache>0</cache>
        <disabled>0</disabled>
        <displayType>select</displayType>
        <freeText>forbidden</freeText>
        <largeStorage>0</largeStorage>
        <multiSelect>0</multiSelect>
        <name>use</name>
        <number>3</number>
        <prettyName>Use this extension</prettyName>
        <relationalStorage>0</relationalStorage>
        <separator> </separator>
        <separators>|, </separators>
        <size>1</size>
        <unmodifiable>0</unmodifiable>
        <values>currentPage|onDemand|always</values>
        <classType>com.xpn.xwiki.objects.classes.StaticListClass</classType>
      </use>
    </class>
    <property>
      <cache>long</cache>
    </property>
    <property>
      <code>#template('colorThemeInit.vm')
        .xwiki-mostviewedpages-cell {
        padding: 10px;
        border-bottom: 1px solid #ddd;
        }
        .xwiki-mostviewedpages-header {
        background-color:  $theme.menuBackgroundColor;
        color: $theme.textColor;
        padding:10px;
        }
</code>
    </property>
    <property>
      <contentType>CSS</contentType>
    </property>
    <property>
      <name/>
    </property>
    <property>
      <parse>1</parse>
    </property>
    <property>
      <use>currentPage</use>
    </property>
  </object>
  <object>
    <name>Analytics.Code.Macros.MostViewedPages</name>
    <number>0</number>
    <className>XWiki.WikiMacroClass</className>
    <guid>46181f3c-348a-441c-8066-514759808b3b</guid>
    <class>
      <name>XWiki.WikiMacroClass</name>
      <customClass/>
      <customMapping/>
      <defaultViewSheet/>
      <defaultEditSheet/>
      <defaultWeb/>
      <nameField/>
      <validationScript/>
      <async_cached>
        <defaultValue>0</defaultValue>
        <disabled>0</disabled>
        <displayFormType>select</displayFormType>
        <displayType/>
        <name>async_cached</name>
        <number>13</number>
        <prettyName>Cached</prettyName>
        <unmodifiable>0</unmodifiable>
        <classType>com.xpn.xwiki.objects.classes.BooleanClass</classType>
      </async_cached>
      <async_context>
        <cache>0</cache>
        <disabled>0</disabled>
        <displayType>select</displayType>
        <freeText>forbidden</freeText>
        <largeStorage>0</largeStorage>
        <multiSelect>1</multiSelect>
        <name>async_context</name>
        <number>14</number>
        <prettyName>Context elements</prettyName>
        <relationalStorage>0</relationalStorage>
        <separator>, </separator>
        <separators>|, </separators>
        <size>5</size>
        <unmodifiable>0</unmodifiable>
        <values>action=Action|doc.reference=Document|icon.theme=Icon theme|locale=Language|rendering.defaultsyntax=Default syntax|rendering.restricted=Restricted|rendering.targetsyntax=Target syntax|request.base=Request base URL|request.parameters=Request parameters|request.url=Request URL|request.wiki=Request wiki|user=User|wiki=Wiki</values>
        <classType>com.xpn.xwiki.objects.classes.StaticListClass</classType>
      </async_context>
      <async_enabled>
        <defaultValue>0</defaultValue>
        <disabled>0</disabled>
        <displayFormType>select</displayFormType>
        <displayType/>
        <name>async_enabled</name>
        <number>12</number>
        <prettyName>Asynchronous rendering</prettyName>
        <unmodifiable>0</unmodifiable>
        <classType>com.xpn.xwiki.objects.classes.BooleanClass</classType>
      </async_enabled>
      <code>
        <disabled>0</disabled>
        <editor>Text</editor>
        <name>code</name>
        <number>10</number>
        <prettyName>Macro code</prettyName>
        <rows>20</rows>
        <size>40</size>
        <unmodifiable>0</unmodifiable>
        <classType>com.xpn.xwiki.objects.classes.TextAreaClass</classType>
      </code>
      <contentDescription>
        <contenttype>PureText</contenttype>
        <disabled>0</disabled>
        <editor>PureText</editor>
        <name>contentDescription</name>
        <number>9</number>
        <prettyName>Content description (Not applicable for "No content" type)</prettyName>
        <rows>5</rows>
        <size>40</size>
        <unmodifiable>0</unmodifiable>
        <classType>com.xpn.xwiki.objects.classes.TextAreaClass</classType>
      </contentDescription>
      <contentJavaType>
        <cache>0</cache>
        <defaultValue>Unknown</defaultValue>
        <disabled>0</disabled>
        <displayType>input</displayType>
        <freeText>allowed</freeText>
        <largeStorage>1</largeStorage>
        <multiSelect>0</multiSelect>
        <name>contentJavaType</name>
        <number>8</number>
        <picker>1</picker>
        <prettyName>Macro content type</prettyName>
        <relationalStorage>0</relationalStorage>
        <separator>|</separator>
        <separators>|</separators>
        <size>1</size>
        <unmodifiable>0</unmodifiable>
        <values>Unknown|Wiki</values>
        <classType>com.xpn.xwiki.objects.classes.StaticListClass</classType>
      </contentJavaType>
      <contentType>
        <cache>0</cache>
        <disabled>0</disabled>
        <displayType>select</displayType>
        <freeText>forbidden</freeText>
        <largeStorage>0</largeStorage>
        <multiSelect>0</multiSelect>
        <name>contentType</name>
        <number>7</number>
        <prettyName>Macro content availability</prettyName>
        <relationalStorage>0</relationalStorage>
        <separator>|</separator>
        <separators>|</separators>
        <size>1</size>
        <unmodifiable>0</unmodifiable>
        <values>Optional|Mandatory|No content</values>
        <classType>com.xpn.xwiki.objects.classes.StaticListClass</classType>
      </contentType>
      <defaultCategory>
        <disabled>0</disabled>
        <name>defaultCategory</name>
        <number>4</number>
        <prettyName>Default category</prettyName>
        <size>30</size>
        <unmodifiable>0</unmodifiable>
        <classType>com.xpn.xwiki.objects.classes.StringClass</classType>
      </defaultCategory>
      <description>
        <contenttype>PureText</contenttype>
        <disabled>0</disabled>
        <editor>PureText</editor>
        <name>description</name>
        <number>3</number>
        <prettyName>Macro description</prettyName>
        <rows>5</rows>
        <size>40</size>
        <unmodifiable>0</unmodifiable>
        <classType>com.xpn.xwiki.objects.classes.TextAreaClass</classType>
      </description>
      <id>
        <disabled>0</disabled>
        <name>id</name>
        <number>1</number>
        <prettyName>Macro id</prettyName>
        <size>30</size>
        <unmodifiable>0</unmodifiable>
        <classType>com.xpn.xwiki.objects.classes.StringClass</classType>
      </id>
      <name>
        <disabled>0</disabled>
        <name>name</name>
        <number>2</number>
        <prettyName>Macro name</prettyName>
        <size>30</size>
        <unmodifiable>0</unmodifiable>
        <classType>com.xpn.xwiki.objects.classes.StringClass</classType>
      </name>
      <priority>
        <disabled>0</disabled>
        <name>priority</name>
        <number>11</number>
        <numberType>integer</numberType>
        <prettyName>Priority</prettyName>
        <size>10</size>
        <unmodifiable>0</unmodifiable>
        <classType>com.xpn.xwiki.objects.classes.NumberClass</classType>
      </priority>
      <supportsInlineMode>
        <disabled>0</disabled>
        <displayFormType>select</displayFormType>
        <displayType>yesno</displayType>
        <name>supportsInlineMode</name>
        <number>5</number>
        <prettyName>Supports inline mode</prettyName>
        <unmodifiable>0</unmodifiable>
        <classType>com.xpn.xwiki.objects.classes.BooleanClass</classType>
      </supportsInlineMode>
      <visibility>
        <cache>0</cache>
        <disabled>0</disabled>
        <displayType>select</displayType>
        <freeText>forbidden</freeText>
        <largeStorage>0</largeStorage>
        <multiSelect>0</multiSelect>
        <name>visibility</name>
        <number>6</number>
        <prettyName>Macro visibility</prettyName>
        <relationalStorage>0</relationalStorage>
        <separator>|</separator>
        <separators>|</separators>
        <size>1</size>
        <unmodifiable>0</unmodifiable>
        <values>Current User|Current Wiki|Global</values>
        <classType>com.xpn.xwiki.objects.classes.StaticListClass</classType>
      </visibility>
    </class>
    <property>
      <async_cached>0</async_cached>
    </property>
    <property>
      <async_context/>
    </property>
    <property>
      <async_enabled>0</async_enabled>
    </property>
    <property>
      <code>{{velocity}}
#set ($discard = $xwiki.jsx.use('Analytics.Code.Macros.MostViewedPages'))
#set ($object =  $xwiki.getDocument("Analytics.Code.Configuration").getObject('Analytics.Code.ConfigurationClass'))
#set ($ip = $object.getProperty("requestAddress").value)
#set ($idSite = $object.getProperty("idSite").value)
#set ($authToken = $object.getProperty("authToken").value)
#set ($dashbord =  $doc.getObject('Analytics.Code.AnalyticsDashboardClass'))
#set ($period = 'range')
##A dashboard will have a date inside and that date will take precedence over the date set by the macro
#if ($dashbord)
  #set ($startTime =  $dashbord.getProperty("startDate"))
  #set ($endTime =  $dashbord.getProperty("endDate"))
#else
  #set ($startTime = $xcontext.macro.params.startDate.toString())
  #set ($endTime = $xcontext.macro.params.endDate.toString())
#end
#set ($rows = $xcontext.macro.params.numberOfRows)
#set ($index = $startTime.indexOf(' '))
#if ($index != -1)
  #set ($startTime = $startTime.substring(0, $index))
#end
#set ($index = $endTime.indexOf(' '))
#if ($index != -1)
  #set ($endTime = $endTime.substring(0, $index))
#end
#set ($startTime = $datetool.toDate('yyyy/MM/dd', $startTime))
#set ($endTime = $datetool.toDate('yyyy/MM/dd', $endTime))
#set ($startTime = $datetool.format('yyyy-MM-dd', $startTime))
#set ($endTime = $datetool.format('yyyy-MM-dd', $endTime))
#set ($date = $startTime + ','+$endTime)
#if(!$startTime || !$endTime)
  #set($period = 'year')
  #set($date = 'last1')
#end
{{html}}
  &lt;div class="mostViewedPages" data-ip-matomo=$ip data-period=$period data-id-site=$idSite data-date=$date data-auth-token=$authToken&gt;
  &lt;div&gt;
{{/html}}

{{/velocity}}</code>
    </property>
    <property>
      <contentDescription/>
    </property>
    <property>
      <contentJavaType>Wiki</contentJavaType>
    </property>
    <property>
      <contentType>No content</contentType>
    </property>
    <property>
      <defaultCategory/>
    </property>
    <property>
      <description>This macro will make a table of the Most Viewed Pages.</description>
    </property>
    <property>
      <id>mostViewedPages</id>
    </property>
    <property>
      <name>Most Viewed Pages</name>
    </property>
    <property>
      <priority/>
    </property>
    <property>
      <supportsInlineMode>1</supportsInlineMode>
    </property>
    <property>
      <visibility>Current Wiki</visibility>
    </property>
  </object>
  <object>
    <name>Analytics.Code.Macros.MostViewedPages</name>
    <number>0</number>
    <className>XWiki.WikiMacroParameterClass</className>
    <guid>a8584a41-4f35-44f7-ab71-7f7e87245f8a</guid>
    <class>
      <name>XWiki.WikiMacroParameterClass</name>
      <customClass/>
      <customMapping/>
      <defaultViewSheet/>
      <defaultEditSheet/>
      <defaultWeb/>
      <nameField/>
      <validationScript/>
      <defaultValue>
        <disabled>0</disabled>
        <name>defaultValue</name>
        <number>4</number>
        <prettyName>Parameter default value</prettyName>
        <size>30</size>
        <unmodifiable>0</unmodifiable>
        <classType>com.xpn.xwiki.objects.classes.StringClass</classType>
      </defaultValue>
      <description>
        <disabled>0</disabled>
        <name>description</name>
        <number>2</number>
        <prettyName>Parameter description</prettyName>
        <rows>5</rows>
        <size>40</size>
        <unmodifiable>0</unmodifiable>
        <classType>com.xpn.xwiki.objects.classes.TextAreaClass</classType>
      </description>
      <mandatory>
        <disabled>0</disabled>
        <displayFormType>select</displayFormType>
        <displayType>yesno</displayType>
        <name>mandatory</name>
        <number>3</number>
        <prettyName>Parameter mandatory</prettyName>
        <unmodifiable>0</unmodifiable>
        <classType>com.xpn.xwiki.objects.classes.BooleanClass</classType>
      </mandatory>
      <name>
        <disabled>0</disabled>
        <name>name</name>
        <number>1</number>
        <prettyName>Parameter name</prettyName>
        <size>30</size>
        <unmodifiable>0</unmodifiable>
        <classType>com.xpn.xwiki.objects.classes.StringClass</classType>
      </name>
      <type>
        <disabled>0</disabled>
        <name>type</name>
        <number>5</number>
        <prettyName>Parameter type</prettyName>
        <size>60</size>
        <unmodifiable>0</unmodifiable>
        <classType>com.xpn.xwiki.objects.classes.StringClass</classType>
      </type>
    </class>
    <property>
      <defaultValue/>
    </property>
    <property>
      <description>Start time of the date interval used for this macro</description>
    </property>
    <property>
      <mandatory>0</mandatory>
    </property>
    <property>
      <name>startDate</name>
    </property>
    <property>
      <type>java.util.Date</type>
    </property>
  </object>
  <object>
    <name>Analytics.Code.Macros.MostViewedPages</name>
    <number>1</number>
    <className>XWiki.WikiMacroParameterClass</className>
    <guid>cf126ff8-9c6a-46f2-bfd0-4885352a960b</guid>
    <class>
      <name>XWiki.WikiMacroParameterClass</name>
      <customClass/>
      <customMapping/>
      <defaultViewSheet/>
      <defaultEditSheet/>
      <defaultWeb/>
      <nameField/>
      <validationScript/>
      <defaultValue>
        <disabled>0</disabled>
        <name>defaultValue</name>
        <number>4</number>
        <prettyName>Parameter default value</prettyName>
        <size>30</size>
        <unmodifiable>0</unmodifiable>
        <classType>com.xpn.xwiki.objects.classes.StringClass</classType>
      </defaultValue>
      <description>
        <disabled>0</disabled>
        <name>description</name>
        <number>2</number>
        <prettyName>Parameter description</prettyName>
        <rows>5</rows>
        <size>40</size>
        <unmodifiable>0</unmodifiable>
        <classType>com.xpn.xwiki.objects.classes.TextAreaClass</classType>
      </description>
      <mandatory>
        <disabled>0</disabled>
        <displayFormType>select</displayFormType>
        <displayType>yesno</displayType>
        <name>mandatory</name>
        <number>3</number>
        <prettyName>Parameter mandatory</prettyName>
        <unmodifiable>0</unmodifiable>
        <classType>com.xpn.xwiki.objects.classes.BooleanClass</classType>
      </mandatory>
      <name>
        <disabled>0</disabled>
        <name>name</name>
        <number>1</number>
        <prettyName>Parameter name</prettyName>
        <size>30</size>
        <unmodifiable>0</unmodifiable>
        <classType>com.xpn.xwiki.objects.classes.StringClass</classType>
      </name>
      <type>
        <disabled>0</disabled>
        <name>type</name>
        <number>5</number>
        <prettyName>Parameter type</prettyName>
        <size>60</size>
        <unmodifiable>0</unmodifiable>
        <classType>com.xpn.xwiki.objects.classes.StringClass</classType>
      </type>
    </class>
    <property>
      <defaultValue/>
    </property>
    <property>
      <description>End time of the date interval used for this macro</description>
    </property>
    <property>
      <mandatory>0</mandatory>
    </property>
    <property>
      <name>endDate</name>
    </property>
    <property>
      <type>java.util.Date</type>
    </property>
  </object>
</xwikidoc>
